eth_retry/ENVIRONMENT_VARIABLES.py
eth_retry/__init__.py
eth_retry/conditional_imports.py
eth_retry/eth_retry.py
eth_retry/py.typed
eth_retry-0.3.6.dist-info/METADATA
eth_retry-0.3.6.dist-info/WHEEL
eth_retry-0.3.6.dist-info/licenses/LICENSE
eth_retry-0.3.6.dist-info/RECORD
