Metadata-Version: 2.4
Name: eth-retry
Version: 0.3.6
Summary: Provides a decorator that automatically catches known transient exceptions that are common in the Ethereum/EVM ecosystem and reattempts to evaluate your decorated function
License: MIT
License-File: LICENSE
Author: BobTheBuidler
Author-email: bobthebuidlerdefi@gmail.com
Requires-Python: >=3.10,<4
Classifier: License :: OSI Approved :: MIT License
Classifier: Programming Language :: Python :: 3
Classifier: Programming Language :: Python :: 3.10
Classifier: Programming Language :: Python :: 3.11
Classifier: Programming Language :: Python :: 3.12
Classifier: Programming Language :: Python :: 3.13
Classifier: Programming Language :: Python :: 3.14
Requires-Dist: typing_extensions (>=4.0.1)
Project-URL: Documentation, https://github.com/BobTheBuidler/eth_retry
Project-URL: Homepage, https://github.com/BobTheBuidler/eth_retry
Project-URL: Repository, https://github.com/BobTheBuidler/eth_retry
